{
  "csv": "Fe_lines.csv",
  "ion_filter": null,
  "n_raw_rows": 20615,
  "n_unique_lines": 19577,
  "wavenumber_min_cm": 5719.909,
  "wavenumber_max_cm": 49998.8,
  "ell_min": 8.658483319246901,
  "ell_max": 10.81297914003176,
  "delta_ell": 2.1544958207848595,
  "best": {
    "k_best": 31.358343337334933,
    "deltaD": 107.12175266766758,
    "D_base": 1028.65711552427,
    "D_harmonic": 921.5353628566024,
    "amplitude": 0.10520042266905424,
    "phase": -1.1044674535582233
  },
  "scan_null_p": 0.0001999600079984003,
  "tail_count_ge": 0,
  "null_n": 5000,
  "branch_report": {
    "n_obs": 10.752733902312999,
    "nearest": [
      {
        "branch": "integer_1_to_40",
        "n": 11.0,
        "k_target": 32.079448802921135,
        "k_error": -0.7211054655862021,
        "abs_k_error": 0.7211054655862021,
        "n_error": -0.24726609768700136,
        "abs_n_error": 0.24726609768700136
      },
      {
        "branch": "koide_10_15_20",
        "n": 10.0,
        "k_target": 29.16313527538285,
        "k_error": 2.1952080619520835,
        "abs_k_error": 2.1952080619520835,
        "n_error": 0.7527339023129986,
        "abs_n_error": 0.7527339023129986
      },
      {
        "branch": "integer_1_to_40",
        "n": 10.0,
        "k_target": 29.16313527538285,
        "k_error": 2.1952080619520835,
        "abs_k_error": 2.1952080619520835,
        "n_error": 0.7527339023129986,
        "abs_n_error": 0.7527339023129986
      },
      {
        "branch": "integer_1_to_40",
        "n": 12.0,
        "k_target": 34.99576233045942,
        "k_error": -3.637418993124488,
        "abs_k_error": 3.637418993124488,
        "n_error": -1.2472660976870014,
        "abs_n_error": 1.2472660976870014
      },
      {
        "branch": "integer_1_to_40",
        "n": 9.0,
        "k_target": 26.246821747844564,
        "k_error": 5.111521589490369,
        "abs_k_error": 5.111521589490369,
        "n_error": 1.7527339023129986,
        "abs_n_error": 1.7527339023129986
      },
      {
        "branch": "integer_1_to_40",
        "n": 13.0,
        "k_target": 37.912075857997706,
        "k_error": -6.5537325206627735,
        "abs_k_error": 6.5537325206627735,
        "n_error": -2.2472660976870014,
        "abs_n_error": 2.2472660976870014
      },
      {
        "branch": "folded_4over9",
        "n": 13.333333333333334,
        "k_target": 38.88418036717714,
        "k_error": -7.525837029842204,
        "abs_k_error": 7.525837029842204,
        "n_error": -2.5805994310203353,
        "abs_n_error": 2.5805994310203353
      },
      {
        "branch": "integer_1_to_40",
        "n": 8.0,
        "k_target": 23.33050822030628,
        "k_error": 8.027835117028651,
        "abs_k_error": 8.027835117028651,
        "n_error": 2.7527339023129986,
        "abs_n_error": 2.7527339023129986
      },
      {
        "branch": "integer_1_to_40",
        "n": 14.0,
        "k_target": 40.82838938553599,
        "k_error": -9.470046048201059,
        "abs_k_error": 9.470046048201059,
        "n_error": -3.2472660976870014,
        "abs_n_error": 3.2472660976870014
      },
      {
        "branch": "integer_1_to_40",
        "n": 7.0,
        "k_target": 20.414194692767996,
        "k_error": 10.944148644566937,
        "abs_k_error": 10.944148644566937,
        "n_error": 3.7527339023129986,
        "abs_n_error": 3.7527339023129986
      }
    ]
  },
  "top_peak_ratios": [
    {
      "k_low": 17.519807923169267,
      "k_high": 65.3343337334934,
      "ratio": 3.7291695217212553,
      "rational": "179/48",
      "rational_error": 2.855054588746242e-06
    },
    {
      "k_low": 27.22268907563025,
      "k_high": 65.3343337334934,
      "ratio": 2.3999955901483916,
      "rational": "12/5",
      "rational_error": 4.409851608322413e-06
    },
    {
      "k_low": 17.519807923169267,
      "k_high": 78.69567827130852,
      "ratio": 4.49181170343977,
      "rational": "274/61",
      "rational_error": 8.424751245073026e-06
    },
    {
      "k_low": 17.519807923169267,
      "k_high": 49.90516206482593,
      "ratio": 2.848499383308209,
      "rational": "94/33",
      "rational_error": 1.453482336044587e-05
    },
    {
      "k_low": 49.90516206482593,
      "k_high": 78.69567827130852,
      "ratio": 1.576904572899377,
      "rational": "41/26",
      "rational_error": 1.850402369996118e-05
    },
    {
      "k_low": 65.3343337334934,
      "k_high": 78.69567827130852,
      "ratio": 1.2045072441132967,
      "rational": "53/44",
      "rational_error": 3.821043215790354e-05
    },
    {
      "k_low": 41.28391356542617,
      "k_high": 78.69567827130852,
      "ratio": 1.9062068363890141,
      "rational": "61/32",
      "rational_error": 4.3163610985885725e-05
    },
    {
      "k_low": 10.266506602641057,
      "k_high": 41.28391356542617,
      "ratio": 4.021223105706267,
      "rational": "189/47",
      "rational_error": 5.349003841370603e-05
    },
    {
      "k_low": 27.22268907563025,
      "k_high": 74.59183673469387,
      "ratio": 2.740061296937358,
      "rational": "137/50",
      "rational_error": 6.129693735790198e-05
    },
    {
      "k_low": 10.266506602641057,
      "k_high": 74.59183673469387,
      "ratio": 7.265551917680074,
      "rational": "465/64",
      "rational_error": 7.308231992642078e-05
    },
    {
      "k_low": 17.519807923169267,
      "k_high": 23.24609843937575,
      "ratio": 1.3268466493079347,
      "rational": "69/52",
      "rational_error": 7.642761514214946e-05
    },
    {
      "k_low": 49.90516206482593,
      "k_high": 65.3343337334934,
      "ratio": 1.309169853984749,
      "rational": "72/55",
      "rational_error": 7.89448938398607e-05
    },
    {
      "k_low": 23.24609843937575,
      "k_high": 41.28391356542617,
      "ratio": 1.7759502168973351,
      "rational": "103/58",
      "rational_error": 8.814793181777247e-05
    },
    {
      "k_low": 27.22268907563025,
      "k_high": 78.69567827130852,
      "ratio": 2.8908120741737044,
      "rational": "159/55",
      "rational_error": 9.701673538664579e-05
    },
    {
      "k_low": 39.21608643457383,
      "k_high": 41.28391356542617,
      "ratio": 1.0527290537851652,
      "rational": "20/19",
      "rational_error": 9.747483779687371e-05
    },
    {
      "k_low": 39.21608643457383,
      "k_high": 74.59183673469387,
      "ratio": 1.9020724278323689,
      "rational": "97/51",
      "rational_error": 0.00011164351864345612
    },
    {
      "k_low": 27.22268907563025,
      "k_high": 39.21608643457383,
      "ratio": 1.4405662249465307,
      "rational": "85/59",
      "rational_error": 0.00011174115516410232
    },
    {
      "k_low": 10.266506602641057,
      "k_high": 31.358343337334933,
      "ratio": 3.0544317118802615,
      "rational": "168/55",
      "rational_error": 0.00011374266519315057
    },
    {
      "k_low": 27.22268907563025,
      "k_high": 49.90516206482593,
      "ratio": 1.8332194121667809,
      "rational": "11/6",
      "rational_error": 0.00011392116655239981
    },
    {
      "k_low": 10.266506602641057,
      "k_high": 23.24609843937575,
      "ratio": 2.264265668849392,
      "rational": "120/53",
      "rational_error": 0.00011472545316548732
    }
  ]
}